djfractions/__init__.py
djfractions/apps.py
djfractions/exceptions.py
djfractions/forms.py
djfractions/models/__init__.py
djfractions/models/fields.py
djfractions/static/css/djfractions.css
djfractions/static/js/djfractions.js
djfractions/templates/djfractions/display_fraction.html
djfractions/templatetags/__init__.py
djfractions/templatetags/fractions.py
django_fractions-5.0.0.dist-info/AUTHORS.rst
django_fractions-5.0.0.dist-info/LICENSE
django_fractions-5.0.0.dist-info/METADATA
django_fractions-5.0.0.dist-info/WHEEL
django_fractions-5.0.0.dist-info/top_level.txt
django_fractions-5.0.0.dist-info/RECORD
